[
  {
    "id": "0VfUNltBpDa5pJGb8qfv",
    "method": "Legacy Import",
    "timestamp": "2026-07-01T14:12:36.933Z",
    "referenceId": "REF-5K4WRW",
    "date": "22-06-2026",
    "userId": "6380351879",
    "status": "Success",
    "amount": 500,
    "accountId": "ACC-VOMFXTGW"
  },
  {
    "id": "CReIWAXG9yI2LakE5BUA",
    "method": "Legacy Import",
    "timestamp": "2026-07-01T14:12:36.597Z",
    "referenceId": "REF-EUJV7P",
    "date": "18-03-2026",
    "userId": "6380351879",
    "status": "Success",
    "amount": 500,
    "accountId": "ACC-VOMFXTGW"
  },
  {
    "id": "IanAwtvtwJ84AGewQqyI",
    "referenceId": "REF-AZSQQ2",
    "timestamp": "2026-07-01T14:12:36.385Z",
    "method": "Legacy Import",
    "amount": 500,
    "accountId": "ACC-VOMFXTGW",
    "userId": "6380351879",
    "status": "Success",
    "date": "27-01-2026"
  },
  {
    "id": "IlymdnLa0BZzOIi4mvEY",
    "date": "18-04-2026",
    "accountId": "ACC-VOMFXTGW",
    "amount": 500,
    "status": "Success",
    "userId": "6380351879",
    "method": "Legacy Import",
    "referenceId": "REF-54TD0K",
    "timestamp": "2026-07-01T14:12:36.742Z"
  },
  {
    "id": "aB6m8GzxbJhAuGXVtEdv",
    "timestamp": "2026-07-01T14:12:36.489Z",
    "referenceId": "REF-4B3NJI",
    "method": "Legacy Import",
    "userId": "6380351879",
    "status": "Success",
    "amount": 500,
    "accountId": "ACC-VOMFXTGW",
    "date": "25-02-2026"
  },
  {
    "id": "l6BtrKsmHK7SOqDxO8ML",
    "timestamp": "2026-07-01T14:12:36.272Z",
    "referenceId": "REF-FYQEOD",
    "method": "Legacy Import",
    "status": "Success",
    "userId": "6380351879",
    "accountId": "ACC-VOMFXTGW",
    "amount": 500,
    "date": "12-12-2025"
  },
  {
    "id": "s7XRKZlKh0JtUkuYvDeC",
    "userId": "6380351879",
    "status": "Success",
    "amount": 500,
    "accountId": "ACC-VOMFXTGW",
    "date": "30-05-2026",
    "timestamp": "2026-07-01T14:12:36.842Z",
    "referenceId": "REF-5BXVG4",
    "method": "Legacy Import"
  }
]